<?xml version="1.0" encoding="utf-8"?>
<items>
<item><name>牧神记</name><author>宅猪</author></item>
<item><name>大王饶命</name><author>会说话的肘子</author></item>
<item><name>诡秘之主</name><author>爱潜水的乌贼</author></item>
<item><name>大医凌然</name><author>志鸟村</author></item>
<item><name>修真聊天群</name><author>圣骑士的传说</author></item>
<item><name>明朝败家子</name><author>上山打老虎额</author></item>
<item><name>圣墟</name><author>辰东</author></item>
<item><name>太初</name><author>高楼大厦</author></item>
<item><name>天下第九</name><author>鹅是老五</author></item>
<item><name>圣武称尊</name><author>小圆源</author></item>
<item><name>汉乡</name><author>孑与2</author></item>
<item><name>全球高武</name><author>老鹰吃小鸡</author></item>
<item><name>凡人修仙之仙界篇</name><author>忘语</author></item>
<item><name>我从凡间来</name><author>想见江南</author></item>
<item><name>全职武神</name><author>流浪的蛤蟆</author></item>
<item><name>三寸人间</name><author>耳根</author></item>
<item><name>民国谍影</name><author>寻青藤</author></item>
<item><name>伏天氏</name><author>净无痕</author></item>
<item><name>天道图书馆</name><author>横扫天涯</author></item>
<item><name>道君</name><author>跃千愁</author></item>
</items>